txHTTP-0.1.2.dist-info/DESCRIPTION.rst
txHTTP-0.1.2.dist-info/METADATA
txHTTP-0.1.2.dist-info/RECORD
txHTTP-0.1.2.dist-info/WHEEL
txHTTP-0.1.2.dist-info/metadata.json
txHTTP-0.1.2.dist-info/top_level.txt
txhttp/__init__.py
txhttp/application.py
txhttp/server.py
txhttp/handlers/__init__.py
txhttp/handlers/generic/__init__.py
txhttp/handlers/generic/base.py
txhttp/utils/__init__.py
txhttp/utils/decorators.py
